travertine-0.49.0.dist-info/METADATA
travertine-0.49.0.dist-info/WHEEL
travertine-0.49.0.dist-info/licenses/LICENSE
travertine/__init__.py
travertine/_lowlevel.cpython-310-x86_64-linux-gnu.so
travertine/_lowlevel.pyi
travertine/aggregators.py
travertine/avm.py
travertine/exceptions.py
travertine/exceptions.pyi
travertine/floats.py
travertine/formulae/__init__.py
travertine/formulae/ast.py
travertine/formulae/expr_parsertab.py
travertine/formulae/expr_parsertab.pyi
travertine/formulae/parser.py
travertine/i18n/__init__.py
travertine/i18n/__init__.pyi
travertine/i18n/locale/en_US/LC_MESSAGES/travertine.mo
travertine/i18n/locale/en_US/LC_MESSAGES/travertine.po
travertine/i18n/locale/es/LC_MESSAGES/travertine.mo
travertine/i18n/locale/es/LC_MESSAGES/travertine.po
travertine/i18n/locale/fr_FR/LC_MESSAGES/travertine.mo
travertine/i18n/locale/fr_FR/LC_MESSAGES/travertine.po
travertine/i18n/locale/travertine.pot
travertine/matrix.py
travertine/meta.py
travertine/predicates.py
travertine/procedures.py
travertine/py.typed
travertine/release.py
travertine/splitters.py
travertine/structs.py
travertine/tables.py
travertine/testing/__init__.py
travertine/testing/base.py
travertine/testing/strategies/__init__.py
travertine/testing/strategies/base.py
travertine/testing/strategies/formulae.py
travertine/testing/strategies/programs.py
travertine/testing/strategies/structs.py
travertine/testing/strategies/tables.py
travertine/testing/tables.py
travertine/topo.py
travertine/types.py
travertine-0.49.0.dist-info/RECORD
