Metadata-Version: 2.4
Name: travertine
Version: 0.49.0
Requires-Dist: xotless>=4.0.0
Requires-Dist: ply
Requires-Dist: immutables
Requires-Dist: xotl-tools>=3.0.0
Requires-Dist: babel>=2.9.0,<3
Requires-Dist: importlib-resources~=6.1.1 ; python_full_version < '3.9'
License-File: LICENSE
Summary: Generating pricing tables from pricing programs
Author-email: Merchise Autrement <info@merchise.de>
Requires-Python: >=3.8
Project-URL: Documentation, https://merchise-autrement.gitlab.io/travertine/
Project-URL: Repository, https://gitlab.merchise.org/mercurio-2018/travertine/
